lb_tech_handler/__init__.py
lb_tech_handler/api_handler.py
lb_tech_handler/common_methods.py
lb_tech_handler/db_handler.py
lb_tech_handler/documentation_handler.py
lb_tech_handler/email_handler.py
lb_tech_handler/excel_handler.py
lb_tech_handler/file_handler.py
lb_tech_handler/minio_handler.py
lb_tech_handler/notification_handler.py
lb_tech_handler/os_handler.py
lb_tech_handler/report_templates.py
lb_tech_handler/sharepoint_handler.py
lb_tech_handler/test.py
lb_tech_handler-1.7.6.dist-info/METADATA
lb_tech_handler-1.7.6.dist-info/WHEEL
lb_tech_handler-1.7.6.dist-info/licenses/LICENSE
lb_tech_handler-1.7.6.dist-info/RECORD
