Metadata-Version: 2.4
Name: lb_tech_handler
Version: 1.7.6
Summary: This package allows faster development by allowing developers to focus on the core logic.
Project-URL: Homepage, https://github.com/code-learnbasics/lb_tech_handler
Project-URL: Issues, https://github.com/code-learnbasics/lb_tech_handler/issues
Author-email: Johnson Rebeiro <rebeirojohnson@gmail.com>, Santhosshe K S <santhosshe23@gmail.com>
License-File: LICENSE
Classifier: License :: OSI Approved :: MIT License
Classifier: Operating System :: OS Independent
Classifier: Programming Language :: Python :: 3
Requires-Python: >=3.9
Requires-Dist: asgiref>=3.8.1
Requires-Dist: certifi>=2025.6.15
Requires-Dist: charset-normalizer>=3.4.2
Requires-Dist: colorama>=0.4.6
Requires-Dist: cryptography>=45.0.4
Requires-Dist: django>=4.2.3
Requires-Dist: djangorestframework>=3.14.0
Requires-Dist: idna>=3.10
Requires-Dist: minio>=7.2.15
Requires-Dist: numpy>=2.3.1
Requires-Dist: ordered-set>=4.1.0
Requires-Dist: pandas>=2.3.0
Requires-Dist: pillow>=11.2.1
Requires-Dist: psycopg2-binary>=2.9.10
Requires-Dist: pyjwt>=2.10.1
Requires-Dist: pylatex>=1.4.2
Requires-Dist: pymsteams>=0.2.5
Requires-Dist: pypdf2>=3.0.1
Requires-Dist: python-barcode>=0.15.1
Requires-Dist: python-dateutil>=2.9.0.post0
Requires-Dist: python-dotenv>=1.1.1
Requires-Dist: pytz>=2025.2
Requires-Dist: qrcode>=8.2
Requires-Dist: redis>=6.2.0
Requires-Dist: requests>=2.32.4
Requires-Dist: six>=1.17.0
Requires-Dist: sqlalchemy>=1.4.47
Requires-Dist: sqlparse>=0.5.3
Requires-Dist: tzdata>=2025.2
Requires-Dist: urllib3>=2.5.0
